ghhops_server/__init__.py
ghhops_server/base.py
ghhops_server/component.py
ghhops_server/logger.py
ghhops_server/params.py
ghhops_server/middlewares/__init__.py
ghhops_server/middlewares/hopsdefault.py
ghhops_server/middlewares/hopsflask.py
ghhops_server-1.5.3.dist-info/WHEEL
ghhops_server-1.5.3.dist-info/METADATA
ghhops_server-1.5.3.dist-info/RECORD
